botrun_hatch/__init__.py
botrun_hatch/models/__init__.py
botrun_hatch/models/hatch.py
botrun_hatch/models/hatch_sharing.py
botrun_hatch/models/hatch_webhook.py
botrun_hatch/models/upload_file.py
botrun_hatch/models/user_setting.py
botrun_hatch-5.12.261.dist-info/METADATA
botrun_hatch-5.12.261.dist-info/WHEEL
botrun_hatch-5.12.261.dist-info/RECORD
