Metadata-Version: 2.4
Name: botrun-hatch
Version: 5.12.261
Author-email: sebastian-hsu <sebastian.hsu@gmail.com>
Requires-Python: >=3.11
Requires-Dist: pydantic-settings>=2.5.2
Provides-Extra: dev
Requires-Dist: build>=1.2.2; extra == 'dev'
Requires-Dist: twine>=5.1.1; extra == 'dev'
